arcade_local_file_management/__init__.py
arcade_local_file_management/tools/__init__.py
arcade_local_file_management/tools/terminal.py
arcade_local_file_management/utils.py
arcade_local_file_management-0.1.8.dist-info/LICENSE
arcade_local_file_management-0.1.8.dist-info/METADATA
arcade_local_file_management-0.1.8.dist-info/WHEEL
arcade_local_file_management-0.1.8.dist-info/RECORD
